{
  "formatVersion": "1",
  "header": {
    "description": "Job Template for Journal entry posting",
    "originalLanguage": "en",
    "abapLanguageVersion": "cloudDevelopment"
  },
  "generalInformation": {
    "catalogName": "ZFICAT_JOURNAL_ENTRY_POST"
  },
  "parameters": {
    "valueRangesParameters": [
      {
        "name": "R_DATE",
        "valueRanges": [
          {
            "sign": "include",
            "option": "between",
            "low": "20240209",
            "high": "20240209"
          }
        ]
      }
    ]
  }
}
